ray_on_aml/__init__.py
ray_on_aml/core.py
ray_on_aml/_telemetry/__init__.py
ray_on_aml/_telemetry/_event_logger.py
ray_on_aml-0.2.4.dist-info/LICENSE
ray_on_aml-0.2.4.dist-info/METADATA
ray_on_aml-0.2.4.dist-info/WHEEL
ray_on_aml-0.2.4.dist-info/top_level.txt
ray_on_aml-0.2.4.dist-info/RECORD
