Metadata-Version: 2.1
Name: ray-on-aml
Version: 0.2.4
Summary: Turn AML cluster into Ray
Home-page: https://github.com/microsoft/ray-on-aml
Author: James Nguyen, Hyun Suk Shin, Dawei Li
Author-email: james.nguyen@microsoft.com,hyssh@microsoft.com, dawei.li@microsoft.com
Project-URL: Bug Tracker, https://github.com/microsoft/ray-on-aml/issues
Classifier: Programming Language :: Python :: 3
Classifier: License :: OSI Approved :: MIT License
Classifier: Operating System :: OS Independent
Requires-Python: >=3.7
License-File: LICENSE
